{
  "customer": [
    {
      "id": 1,
      "name": "Nguyễn Anh Tâm ",
      "dayOfBirth": "2002-07-01",
      "gender": 1,
      "nationalId": "344343432",
      "phone": "0987654321",
      "mail": "thihao07@gmail.com",
      "address": "23 Nguyễn Hoàng, Đà Nẵng",
      "customerType": {
        "id": 1,
        "name": "Kim cương"
      }
    },
    {
      "id": 2,
      "name": "Nguyễn Anh Tâm ",
      "dayOfBirth": "2002-07-01",
      "gender": 1,
      "nationalId": "344343432",
      "phone": "0987654321",
      "mail": "thihao07@gmail.com",
      "address": "23 Nguyễn Hoàng, Đà Nẵng",
      "customerType": {
        "id": 2,
        "name": "Kim cương"
      }
    },
    {
      "id": 3,
      "name": "Nguyễn Anh Tâm ",
      "dayOfBirth": "2002-07-01",
      "gender": 0,
      "nationalId": "344343432",
      "phone": "0987654321",
      "mail": "thihao07@gmail.com",
      "address": "23 Nguyễn Hoàng, Đà Nẵng",
      "customerType": {
        "id": 1,
        "name": "Kim cương"
      }
    },
    {
      "id": 4,
      "name": "Nguyễn Anh Tâm ",
      "dayOfBirth": "2002-07-01",
      "gender": 0,
      "nationalId": "344343432",
      "phone": "0987654321",
      "mail": "thihao07@gmail.com",
      "address": "23 Nguyễn Hoàng, Đà Nẵng",
      "customerType": {
        "id": 1,
        "name": "Kim cương"
      }
    },
    {
      "id": 5,
      "name": "Nguyễn Anh Tâm ",
      "dayOfBirth": "2002-07-01",
      "gender": 0,
      "nationalId": "344343432",
      "phone": "0987654321",
      "mail": "thihao07@gmail.com",
      "address": "23 Nguyễn Hoàng, Đà Nẵng",
      "customerType": {
        "id": 2,
        "name": "Kim cương"
      }
    },
    {
      "id": "Kh-1234",
      "name": "tâm nguyễn",
      "dayOfBirth": "2022-06-01",
      "gender": "",
      "nationalId": "123456789",
      "phone": "0903709673",
      "mail": "nguyenanhtam12344321@gmail.com",
      "address": "điện thọ",
      "salary": "123123"
    }
  ]
}